tyr_agent/__init__.py
tyr_agent/py.typed
tyr_agent/core/__init__.py
tyr_agent/core/agent.py
tyr_agent/core/ai_config.py
tyr_agent/entities/__init__.py
tyr_agent/entities/entities.py
tyr_agent/mixins/__init__.py
tyr_agent/mixins/gemini_file_mixins.py
tyr_agent/mixins/gpt_file_mixins.py
tyr_agent/models/__init__.py
tyr_agent/models/gemini_model.py
tyr_agent/models/gpt_model.py
tyr_agent/storage/__init__.py
tyr_agent/storage/interaction_history.py
tyr_agent/utils/__init__.py
tyr_agent/utils/gpt_function_format_utils.py
tyr_agent/utils/image_utils.py
tyr_agent-1.0.2.dist-info/licenses/LICENSE
tyr_agent-1.0.2.dist-info/METADATA
tyr_agent-1.0.2.dist-info/WHEEL
tyr_agent-1.0.2.dist-info/top_level.txt
tyr_agent-1.0.2.dist-info/RECORD
