Metadata-Version: 2.4
Name: tyr-agent
Version: 1.0.2
Summary: Biblioteca para criação de agentes LLM com suporte a Gemini e GPT, histórico persistente, execução de funções e roteamento entre múltiplos agentes.
Author-email: Witor Oliveira <witoredson@gmail.com>
License: MIT
Project-URL: Homepage, https://github.com/Drarlian/tyr-agent
Project-URL: Source, https://github.com/Drarlian/tyr-agent
Project-URL: Issues, https://github.com/Drarlian/tyr-agent/issues
Keywords: llm,agent,gemini,openai,function-calling,multi-agent,memory,orchestration
Requires-Python: >=3.10
License-File: LICENSE
Requires-Dist: google-genai
Requires-Dist: openai
Requires-Dist: python-dotenv
Dynamic: license-file
